README.txt
license.txt
setup.py
ml4py/__init__.py
ml4py/object_classify.py
ml4py/recognize_numbers.py
ml4py.egg-info/PKG-INFO
ml4py.egg-info/SOURCES.txt
ml4py.egg-info/dependency_links.txt
ml4py.egg-info/top_level.txt