Metadata-Version: 2.1
Name: ml4py
Version: 1.0.0
Summary: A python module to give easy access to AI and ML, with one line of code!
Author: Viraj Khanna
Author-email: viraj@virajkhanna.in
Classifier: Development Status :: 4 - Beta
Classifier: Intended Audience :: Science/Research
Classifier: Intended Audience :: Developers
Classifier: Natural Language :: English
Classifier: Programming Language :: Python :: 3.10
Classifier: Topic :: Scientific/Engineering :: Artificial Intelligence
Requires: tensorflow
Requires: numpy
Requires: matplotlib
License-File: license.txt
